tests/__init__.py
uweb3plugins/__init__.py
uweb3plugins/core/__init__.py
uweb3plugins/core/models/__init__.py
uweb3plugins/core/models/api_model.py
uweb3plugins/core/models/richmodel.py
uweb3plugins/core/models/richversionrecord.py
uweb3plugins/core/pagemakers/__init__.py
uweb3plugins/core/pagemakers/restricted.py
uweb3plugins/core/paginators/__init__.py
uweb3plugins/core/paginators/columns.py
uweb3plugins/core/paginators/helpers.py
uweb3plugins/core/paginators/html_elements.py
uweb3plugins/core/paginators/table.py
uweb3plugins/core/paginators/model/__init__.py
uweb3plugins/core/paginators/model/searchable_table.py
uweb3plugins/core/paginators/templates/element.html
uweb3plugins/core/paginators/templates/pagination.html
uweb3plugins/core/paginators/templates/search_field.html
uweb3plugins/core/paginators/templates/sortable_head.html
uwebthreeplugins-0.0.4.dist-info/METADATA
uwebthreeplugins-0.0.4.dist-info/WHEEL
uwebthreeplugins-0.0.4.dist-info/top_level.txt
uwebthreeplugins-0.0.4.dist-info/RECORD
